[{"py/object": "db.dataclasses.junction_data.JunctionData", "idnum": 1, "coordinates": [{"py/object": "server.geometry.point.Point", "_Point__x": 19.32541, "_Point__y": -1.32541}, {"py/object": "server.geometry.point.Point", "_Point__x": 21.32541, "_Point__y": -1.32541}, {"py/object": "server.geometry.point.Point", "_Point__x": 20.942410000000002, "_Point__y": 1.8515899999999998}, {"py/object": "server.geometry.point.Point", "_Point__x": 19.32541, "_Point__y": 0.6746}], "goes_to": [{"py/tuple": [{"py/object": "db.dataclasses.road_lane.RoadLane", "road_id": 30, "lane_num": 0}, {"py/object": "db.dataclasses.road_lane.RoadLane", "road_id": 82, "lane_num": 1}]}, {"py/tuple": [{"py/object": "db.dataclasses.road_lane.RoadLane", "road_id": 67, "lane_num": 0}, {"py/object": "db.dataclasses.road_lane.RoadLane", "road_id": 82, "lane_num": 1}]}], "traffic_lights": [[{"py/object": "db.dataclasses.road_lane.RoadLane", "road_id": 30, "lane_num": 0}], [{"py/object": "db.dataclasses.road_lane.RoadLane", "road_id": 67, "lane_num": 0}]], "traffic_lights_coords": [{"py/object": "server.geometry.point.Point", "_Point__x": 22.942410000000002, "_Point__y": 3.85159}, {"py/object": "server.geometry.point.Point", "_Point__x": 17.32541, "_Point__y": 2.6746}], "num_traffic_lights": 2}, {"py/object": "db.dataclasses.junction_data.JunctionData", "idnum": 2, "coordinates": [{"py/object": "server.geometry.point.Point", "_Point__x": 38.75697, "_Point__y": -0.153}, {"py/object": "server.geometry.point.Point", "_Point__x": 40.489020000000004, "_Point__y": -1.153}, {"py/object": "server.geometry.point.Point", "_Point__x": 42.41187, "_Point__y": -0.29685000000000006}, {"py/object": "server.geometry.point.Point", "_Point__x": 38.75697, "_Point__y": 2.15299}], "goes_to": [{"py/tuple": [{"py/object": "db.dataclasses.road_lane.RoadLane", "road_id": 82, "lane_num": 0}, {"py/object": "db.dataclasses.road_lane.RoadLane", "road_id": 15, "lane_num": 0}]}, {"py/tuple": [{"py/object": "db.dataclasses.road_lane.RoadLane", "road_id": 82, "lane_num": 1}, {"py/object": "db.dataclasses.road_lane.RoadLane", "road_id": 27, "lane_num": 2}]}], "traffic_lights": [], "traffic_lights_coords": [], "num_traffic_lights": 0}, {"py/object": "db.dataclasses.junction_data.JunctionData", "idnum": 5, "coordinates": [{"py/object": "server.geometry.point.Point", "_Point__x": 98.83399, "_Point__y": -1.5112}, {"py/object": "server.geometry.point.Point", "_Point__x": 100.8036, "_Point__y": -1.1638700000000002}, {"py/object": "server.geometry.point.Point", "_Point__x": 100.63993, "_Point__y": 0.82938}, {"py/object": "server.geometry.point.Point", "_Point__x": 98.83399, "_Point__y": 1.68879}], "goes_to": [{"py/tuple": [{"py/object": "db.dataclasses.road_lane.RoadLane", "road_id": 70, "lane_num": 0}, {"py/object": "db.dataclasses.road_lane.RoadLane", "road_id": 101, "lane_num": 0}]}, {"py/tuple": [{"py/object": "db.dataclasses.road_lane.RoadLane", "road_id": 70, "lane_num": 1}, {"py/object": "db.dataclasses.road_lane.RoadLane", "road_id": 40, "lane_num": 1}]}], "traffic_lights": [], "traffic_lights_coords": [], "num_traffic_lights": 0}, {"py/object": "db.dataclasses.junction_data.JunctionData", "idnum": 6, "coordinates": [{"py/object": "server.geometry.point.Point", "_Point__x": 118.83399, "_Point__y": -1.5112}, {"py/object": "server.geometry.point.Point", "_Point__x": 120.8036, "_Point__y": -1.1638700000000002}, {"py/object": "server.geometry.point.Point", "_Point__x": 120.63993, "_Point__y": 0.82938}, {"py/object": "server.geometry.point.Point", "_Point__x": 118.83399, "_Point__y": 1.68879}], "goes_to": [{"py/tuple": [{"py/object": "db.dataclasses.road_lane.RoadLane", "road_id": 60, "lane_num": 0}, {"py/object": "db.dataclasses.road_lane.RoadLane", "road_id": 41, "lane_num": 0}]}, {"py/tuple": [{"py/object": "db.dataclasses.road_lane.RoadLane", "road_id": 60, "lane_num": 1}, {"py/object": "db.dataclasses.road_lane.RoadLane", "road_id": 70, "lane_num": 1}]}], "traffic_lights": [], "traffic_lights_coords": [], "num_traffic_lights": 0}, {"py/object": "db.dataclasses.junction_data.JunctionData", "idnum": 10, "coordinates": [{"py/object": "server.geometry.point.Point", "_Point__x": -1.32541, "_Point__y": 19.32541}, {"py/object": "server.geometry.point.Point", "_Point__x": 0.67459, "_Point__y": 19.32541}, {"py/object": "server.geometry.point.Point", "_Point__x": 1.85159, "_Point__y": 20.94243}, {"py/object": "server.geometry.point.Point", "_Point__x": -1.32541, "_Point__y": 21.32541}], "goes_to": [{"py/tuple": [{"py/object": "db.dataclasses.road_lane.RoadLane", "road_id": 7, "lane_num": 0}, {"py/object": "db.dataclasses.road_lane.RoadLane", "road_id": 94, "lane_num": 1}]}, {"py/tuple": [{"py/object": "db.dataclasses.road_lane.RoadLane", "road_id": 7, "lane_num": 1}, {"py/object": "db.dataclasses.road_lane.RoadLane", "road_id": 67, "lane_num": 0}]}], "traffic_lights": [], "traffic_lights_coords": [], "num_traffic_lights": 0}, {"py/object": "db.dataclasses.junction_data.JunctionData", "idnum": 12, "coordinates": [{"py/object": "server.geometry.point.Point", "_Point__x": 38.75697, "_Point__y": 19.847}, {"py/object": "server.geometry.point.Point", "_Point__x": 40.489020000000004, "_Point__y": 18.847}, {"py/object": "server.geometry.point.Point", "_Point__x": 42.41187, "_Point__y": 19.70315}, {"py/object": "server.geometry.point.Point", "_Point__x": 38.75697, "_Point__y": 22.15299}], "goes_to": [{"py/tuple": [{"py/object": "db.dataclasses.road_lane.RoadLane", "road_id": 27, "lane_num": 0}, {"py/object": "db.dataclasses.road_lane.RoadLane", "road_id": 62, "lane_num": 0}]}, {"py/tuple": [{"py/object": "db.dataclasses.road_lane.RoadLane", "road_id": 27, "lane_num": 1}, {"py/object": "db.dataclasses.road_lane.RoadLane", "road_id": 38, "lane_num": 2}]}, {"py/tuple": [{"py/object": "db.dataclasses.road_lane.RoadLane", "road_id": 27, "lane_num": 2}, {"py/object": "db.dataclasses.road_lane.RoadLane", "road_id": 30, "lane_num": 0}]}], "traffic_lights": [], "traffic_lights_coords": [], "num_traffic_lights": 0}, {"py/object": "db.dataclasses.junction_data.JunctionData", "idnum": 13, "coordinates": [{"py/object": "server.geometry.point.Point", "_Point__x": 58.67459, "_Point__y": 19.32541}, {"py/object": "server.geometry.point.Point", "_Point__x": 60.67459, "_Point__y": 19.32541}, {"py/object": "server.geometry.point.Point", "_Point__x": 61.85159, "_Point__y": 20.94243}, {"py/object": "server.geometry.point.Point", "_Point__x": 58.67459, "_Point__y": 21.32541}], "goes_to": [{"py/tuple": [{"py/object": "db.dataclasses.road_lane.RoadLane", "road_id": 15, "lane_num": 0}, {"py/object": "db.dataclasses.road_lane.RoadLane", "road_id": 99, "lane_num": 1}]}, {"py/tuple": [{"py/object": "db.dataclasses.road_lane.RoadLane", "road_id": 19, "lane_num": 0}, {"py/object": "db.dataclasses.road_lane.RoadLane", "road_id": 99, "lane_num": 1}]}, {"py/tuple": [{"py/object": "db.dataclasses.road_lane.RoadLane", "road_id": 62, "lane_num": 0}, {"py/object": "db.dataclasses.road_lane.RoadLane", "road_id": 99, "lane_num": 1}]}], "traffic_lights": [[{"py/object": "db.dataclasses.road_lane.RoadLane", "road_id": 15, "lane_num": 0}], [{"py/object": "db.dataclasses.road_lane.RoadLane", "road_id": 19, "lane_num": 0}], [{"py/object": "db.dataclasses.road_lane.RoadLane", "road_id": 62, "lane_num": 0}]], "traffic_lights_coords": [{"py/object": "server.geometry.point.Point", "_Point__x": 56.67459, "_Point__y": 17.32541}, {"py/object": "server.geometry.point.Point", "_Point__x": 62.67459, "_Point__y": 17.32541}, {"py/object": "server.geometry.point.Point", "_Point__x": 56.67459, "_Point__y": 23.32541}], "num_traffic_lights": 3}, {"py/object": "db.dataclasses.junction_data.JunctionData", "idnum": 16, "coordinates": [{"py/object": "server.geometry.point.Point", "_Point__x": 119.32541, "_Point__y": 18.67459}, {"py/object": "server.geometry.point.Point", "_Point__x": 121.32541, "_Point__y": 18.67459}, {"py/object": "server.geometry.point.Point", "_Point__x": 120.94241000000001, "_Point__y": 21.85159}, {"py/object": "server.geometry.point.Point", "_Point__x": 119.32541, "_Point__y": 20.6746}], "goes_to": [{"py/tuple": [{"py/object": "db.dataclasses.road_lane.RoadLane", "road_id": 8, "lane_num": 0}, {"py/object": "db.dataclasses.road_lane.RoadLane", "road_id": 37, "lane_num": 1}]}, {"py/tuple": [{"py/object": "db.dataclasses.road_lane.RoadLane", "road_id": 41, "lane_num": 0}, {"py/object": "db.dataclasses.road_lane.RoadLane", "road_id": 37, "lane_num": 1}]}, {"py/tuple": [{"py/object": "db.dataclasses.road_lane.RoadLane", "road_id": 101, "lane_num": 0}, {"py/object": "db.dataclasses.road_lane.RoadLane", "road_id": 37, "lane_num": 1}]}], "traffic_lights": [[{"py/object": "db.dataclasses.road_lane.RoadLane", "road_id": 8, "lane_num": 0}], [{"py/object": "db.dataclasses.road_lane.RoadLane", "road_id": 41, "lane_num": 0}], [{"py/object": "db.dataclasses.road_lane.RoadLane", "road_id": 101, "lane_num": 0}]], "traffic_lights_coords": [{"py/object": "server.geometry.point.Point", "_Point__x": 122.94241000000001, "_Point__y": 23.85159}, {"py/object": "server.geometry.point.Point", "_Point__x": 117.32541, "_Point__y": 16.67459}, {"py/object": "server.geometry.point.Point", "_Point__x": 117.32541, "_Point__y": 22.6746}], "num_traffic_lights": 3}, {"py/object": "db.dataclasses.junction_data.JunctionData", "idnum": 17, "coordinates": [{"py/object": "server.geometry.point.Point", "_Point__x": 138.71423, "_Point__y": 18.58929}, {"py/object": "server.geometry.point.Point", "_Point__x": 141.86560999999998, "_Point__y": 19.14499}, {"py/object": "server.geometry.point.Point", "_Point__x": 140.70566, "_Point__y": 20.77426}, {"py/object": "server.geometry.point.Point", "_Point__x": 138.71423, "_Point__y": 20.5893}], "goes_to": [{"py/tuple": [{"py/object": "db.dataclasses.road_lane.RoadLane", "road_id": 37, "lane_num": 0}, {"py/object": "db.dataclasses.road_lane.RoadLane", "road_id": 60, "lane_num": 1}]}, {"py/tuple": [{"py/object": "db.dataclasses.road_lane.RoadLane", "road_id": 37, "lane_num": 1}, {"py/object": "db.dataclasses.road_lane.RoadLane", "road_id": 18, "lane_num": 0}]}, {"py/tuple": [{"py/object": "db.dataclasses.road_lane.RoadLane", "road_id": 97, "lane_num": 0}, {"py/object": "db.dataclasses.road_lane.RoadLane", "road_id": 60, "lane_num": 1}]}, {"py/tuple": [{"py/object": "db.dataclasses.road_lane.RoadLane", "road_id": 97, "lane_num": 1}, {"py/object": "db.dataclasses.road_lane.RoadLane", "road_id": 18, "lane_num": 0}]}], "traffic_lights": [[{"py/object": "db.dataclasses.road_lane.RoadLane", "road_id": 37, "lane_num": 0}, {"py/object": "db.dataclasses.road_lane.RoadLane", "road_id": 37, "lane_num": 1}], [{"py/object": "db.dataclasses.road_lane.RoadLane", "road_id": 97, "lane_num": 0}, {"py/object": "db.dataclasses.road_lane.RoadLane", "road_id": 97, "lane_num": 1}]], "traffic_lights_coords": [{"py/object": "server.geometry.point.Point", "_Point__x": 136.71423, "_Point__y": 22.5893}, {"py/object": "server.geometry.point.Point", "_Point__x": 142.70566, "_Point__y": 22.77426}], "num_traffic_lights": 2}, {"py/object": "db.dataclasses.junction_data.JunctionData", "idnum": 19, "coordinates": [{"py/object": "server.geometry.point.Point", "_Point__x": 178.67459, "_Point__y": 19.32541}, {"py/object": "server.geometry.point.Point", "_Point__x": 180.67459, "_Point__y": 19.32541}, {"py/object": "server.geometry.point.Point", "_Point__x": 181.85159, "_Point__y": 20.94243}, {"py/object": "server.geometry.point.Point", "_Point__x": 178.67459, "_Point__y": 21.32541}], "goes_to": [{"py/tuple": [{"py/object": "db.dataclasses.road_lane.RoadLane", "road_id": 4, "lane_num": 0}, {"py/object": "db.dataclasses.road_lane.RoadLane", "road_id": 29, "lane_num": 1}]}, {"py/tuple": [{"py/object": "db.dataclasses.road_lane.RoadLane", "road_id": 18, "lane_num": 0}, {"py/object": "db.dataclasses.road_lane.RoadLane", "road_id": 29, "lane_num": 1}]}], "traffic_lights": [[{"py/object": "db.dataclasses.road_lane.RoadLane", "road_id": 4, "lane_num": 0}], [{"py/object": "db.dataclasses.road_lane.RoadLane", "road_id": 18, "lane_num": 0}]], "traffic_lights_coords": [{"py/object": "server.geometry.point.Point", "_Point__x": 176.67459, "_Point__y": 23.32541}, {"py/object": "server.geometry.point.Point", "_Point__x": 176.67459, "_Point__y": 17.32541}], "num_traffic_lights": 2}, {"py/object": "db.dataclasses.junction_data.JunctionData", "idnum": 20, "coordinates": [{"py/object": "server.geometry.point.Point", "_Point__x": -0.48902, "_Point__y": 38.84701}, {"py/object": "server.geometry.point.Point", "_Point__x": 1.24303, "_Point__y": 37.84701}, {"py/object": "server.geometry.point.Point", "_Point__x": 0.94885, "_Point__y": 42.237159999999996}, {"py/object": "server.geometry.point.Point", "_Point__x": -0.48902, "_Point__y": 40.84701}], "goes_to": [{"py/tuple": [{"py/object": "db.dataclasses.road_lane.RoadLane", "road_id": 94, "lane_num": 0}, {"py/object": "db.dataclasses.road_lane.RoadLane", "road_id": 32, "lane_num": 2}]}, {"py/tuple": [{"py/object": "db.dataclasses.road_lane.RoadLane", "road_id": 94, "lane_num": 1}, {"py/object": "db.dataclasses.road_lane.RoadLane", "road_id": 0, "lane_num": 0}]}], "traffic_lights": [], "traffic_lights_coords": [], "num_traffic_lights": 0}, {"py/object": "db.dataclasses.junction_data.JunctionData", "idnum": 21, "coordinates": [{"py/object": "server.geometry.point.Point", "_Point__x": 18.71423, "_Point__y": 38.58929}, {"py/object": "server.geometry.point.Point", "_Point__x": 21.86561, "_Point__y": 39.14499}, {"py/object": "server.geometry.point.Point", "_Point__x": 20.70566, "_Point__y": 40.77426}, {"py/object": "server.geometry.point.Point", "_Point__x": 18.71423, "_Point__y": 40.5893}], "goes_to": [{"py/tuple": [{"py/object": "db.dataclasses.road_lane.RoadLane", "road_id": 22, "lane_num": 0}, {"py/object": "db.dataclasses.road_lane.RoadLane", "road_id": 7, "lane_num": 1}]}, {"py/tuple": [{"py/object": "db.dataclasses.road_lane.RoadLane", "road_id": 46, "lane_num": 0}, {"py/object": "db.dataclasses.road_lane.RoadLane", "road_id": 7, "lane_num": 1}]}], "traffic_lights": [[{"py/object": "db.dataclasses.road_lane.RoadLane", "road_id": 22, "lane_num": 0}], [{"py/object": "db.dataclasses.road_lane.RoadLane", "road_id": 46, "lane_num": 0}]], "traffic_lights_coords": [{"py/object": "server.geometry.point.Point", "_Point__x": 22.70566, "_Point__y": 42.77426}, {"py/object": "server.geometry.point.Point", "_Point__x": 23.86561, "_Point__y": 37.14499}], "num_traffic_lights": 2}, {"py/object": "db.dataclasses.junction_data.JunctionData", "idnum": 22, "coordinates": [{"py/object": "server.geometry.point.Point", "_Point__x": 39.32541, "_Point__y": 38.67459}, {"py/object": "server.geometry.point.Point", "_Point__x": 41.32541, "_Point__y": 38.67459}, {"py/object": "server.geometry.point.Point", "_Point__x": 40.942409999999995, "_Point__y": 41.85159}, {"py/object": "server.geometry.point.Point", "_Point__x": 39.32541, "_Point__y": 40.6746}], "goes_to": [{"py/tuple": [{"py/object": "db.dataclasses.road_lane.RoadLane", "road_id": 38, "lane_num": 0}, {"py/object": "db.dataclasses.road_lane.RoadLane", "road_id": 50, "lane_num": 1}]}, {"py/tuple": [{"py/object": "db.dataclasses.road_lane.RoadLane", "road_id": 38, "lane_num": 1}, {"py/object": "db.dataclasses.road_lane.RoadLane", "road_id": 61, "lane_num": 0}]}, {"py/tuple": [{"py/object": "db.dataclasses.road_lane.RoadLane", "road_id": 38, "lane_num": 2}, {"py/object": "db.dataclasses.road_lane.RoadLane", "road_id": 46, "lane_num": 0}]}], "traffic_lights": [], "traffic_lights_coords": [], "num_traffic_lights": 0}, {"py/object": "db.dataclasses.junction_data.JunctionData", "idnum": 23, "coordinates": [{"py/object": "server.geometry.point.Point", "_Point__x": 59.0, "_Point__y": 39.0}, {"py/object": "server.geometry.point.Point", "_Point__x": 61.0, "_Point__y": 39.0}, {"py/object": "server.geometry.point.Point", "_Point__x": 61.0, "_Point__y": 41.0}, {"py/object": "server.geometry.point.Point", "_Point__x": 59.0, "_Point__y": 41.0}], "goes_to": [{"py/tuple": [{"py/object": "db.dataclasses.road_lane.RoadLane", "road_id": 50, "lane_num": 0}, {"py/object": "db.dataclasses.road_lane.RoadLane", "road_id": 12, "lane_num": 0}]}, {"py/tuple": [{"py/object": "db.dataclasses.road_lane.RoadLane", "road_id": 50, "lane_num": 1}, {"py/object": "db.dataclasses.road_lane.RoadLane", "road_id": 45, "lane_num": 0}]}, {"py/tuple": [{"py/object": "db.dataclasses.road_lane.RoadLane", "road_id": 99, "lane_num": 0}, {"py/object": "db.dataclasses.road_lane.RoadLane", "road_id": 12, "lane_num": 0}]}, {"py/tuple": [{"py/object": "db.dataclasses.road_lane.RoadLane", "road_id": 99, "lane_num": 1}, {"py/object": "db.dataclasses.road_lane.RoadLane", "road_id": 45, "lane_num": 0}]}], "traffic_lights": [[{"py/object": "db.dataclasses.road_lane.RoadLane", "road_id": 50, "lane_num": 0}, {"py/object": "db.dataclasses.road_lane.RoadLane", "road_id": 50, "lane_num": 1}], [{"py/object": "db.dataclasses.road_lane.RoadLane", "road_id": 99, "lane_num": 0}, {"py/object": "db.dataclasses.road_lane.RoadLane", "road_id": 99, "lane_num": 1}]], "traffic_lights_coords": [{"py/object": "server.geometry.point.Point", "_Point__x": 57.0, "_Point__y": 43.0}, {"py/object": "server.geometry.point.Point", "_Point__x": 57.0, "_Point__y": 37.0}], "num_traffic_lights": 2}, {"py/object": "db.dataclasses.junction_data.JunctionData", "idnum": 25, "coordinates": [{"py/object": "server.geometry.point.Point", "_Point__x": 99.0, "_Point__y": 39.0}, {"py/object": "server.geometry.point.Point", "_Point__x": 101.0, "_Point__y": 39.0}, {"py/object": "server.geometry.point.Point", "_Point__x": 101.0, "_Point__y": 41.0}, {"py/object": "server.geometry.point.Point", "_Point__x": 99.0, "_Point__y": 41.0}], "goes_to": [{"py/tuple": [{"py/object": "db.dataclasses.road_lane.RoadLane", "road_id": 40, "lane_num": 0}, {"py/object": "db.dataclasses.road_lane.RoadLane", "road_id": 8, "lane_num": 0}]}, {"py/tuple": [{"py/object": "db.dataclasses.road_lane.RoadLane", "road_id": 40, "lane_num": 1}, {"py/object": "db.dataclasses.road_lane.RoadLane", "road_id": 19, "lane_num": 0}]}, {"py/tuple": [{"py/object": "db.dataclasses.road_lane.RoadLane", "road_id": 92, "lane_num": 0}, {"py/object": "db.dataclasses.road_lane.RoadLane", "road_id": 19, "lane_num": 0}]}, {"py/tuple": [{"py/object": "db.dataclasses.road_lane.RoadLane", "road_id": 92, "lane_num": 1}, {"py/object": "db.dataclasses.road_lane.RoadLane", "road_id": 8, "lane_num": 0}]}], "traffic_lights": [[{"py/object": "db.dataclasses.road_lane.RoadLane", "road_id": 40, "lane_num": 0}, {"py/object": "db.dataclasses.road_lane.RoadLane", "road_id": 40, "lane_num": 1}], [{"py/object": "db.dataclasses.road_lane.RoadLane", "road_id": 92, "lane_num": 0}, {"py/object": "db.dataclasses.road_lane.RoadLane", "road_id": 92, "lane_num": 1}]], "traffic_lights_coords": [{"py/object": "server.geometry.point.Point", "_Point__x": 97.0, "_Point__y": 37.0}, {"py/object": "server.geometry.point.Point", "_Point__x": 103.0, "_Point__y": 43.0}], "num_traffic_lights": 2}, {"py/object": "db.dataclasses.junction_data.JunctionData", "idnum": 27, "coordinates": [{"py/object": "server.geometry.point.Point", "_Point__x": 138.53122, "_Point__y": 37.00391}, {"py/object": "server.geometry.point.Point", "_Point__x": 140.98255999999998, "_Point__y": 39.060829999999996}, {"py/object": "server.geometry.point.Point", "_Point__x": 140.48984, "_Point__y": 40.99919}, {"py/object": "server.geometry.point.Point", "_Point__x": 138.53122, "_Point__y": 41.40392}], "goes_to": [{"py/tuple": [{"py/object": "db.dataclasses.road_lane.RoadLane", "road_id": 20, "lane_num": 0}, {"py/object": "db.dataclasses.road_lane.RoadLane", "road_id": 6, "lane_num": 2}]}, {"py/tuple": [{"py/object": "db.dataclasses.road_lane.RoadLane", "road_id": 20, "lane_num": 1}, {"py/object": "db.dataclasses.road_lane.RoadLane", "road_id": 97, "lane_num": 1}]}, {"py/tuple": [{"py/object": "db.dataclasses.road_lane.RoadLane", "road_id": 20, "lane_num": 2}, {"py/object": "db.dataclasses.road_lane.RoadLane", "road_id": 25, "lane_num": 0}]}], "traffic_lights": [], "traffic_lights_coords": [], "num_traffic_lights": 0}, {"py/object": "db.dataclasses.junction_data.JunctionData", "idnum": 29, "coordinates": [{"py/object": "server.geometry.point.Point", "_Point__x": 179.0, "_Point__y": 39.0}, {"py/object": "server.geometry.point.Point", "_Point__x": 181.0, "_Point__y": 39.0}, {"py/object": "server.geometry.point.Point", "_Point__x": 181.0, "_Point__y": 41.0}, {"py/object": "server.geometry.point.Point", "_Point__x": 179.0, "_Point__y": 41.0}], "goes_to": [{"py/tuple": [{"py/object": "db.dataclasses.road_lane.RoadLane", "road_id": 29, "lane_num": 0}, {"py/object": "db.dataclasses.road_lane.RoadLane", "road_id": 44, "lane_num": 0}]}, {"py/tuple": [{"py/object": "db.dataclasses.road_lane.RoadLane", "road_id": 29, "lane_num": 1}, {"py/object": "db.dataclasses.road_lane.RoadLane", "road_id": 4, "lane_num": 0}]}], "traffic_lights": [], "traffic_lights_coords": [], "num_traffic_lights": 0}, {"py/object": "db.dataclasses.junction_data.JunctionData", "idnum": 32, "coordinates": [{"py/object": "server.geometry.point.Point", "_Point__x": 39.0, "_Point__y": 59.0}, {"py/object": "server.geometry.point.Point", "_Point__x": 41.0, "_Point__y": 59.0}, {"py/object": "server.geometry.point.Point", "_Point__x": 41.0, "_Point__y": 61.0}, {"py/object": "server.geometry.point.Point", "_Point__x": 39.0, "_Point__y": 61.0}], "goes_to": [{"py/tuple": [{"py/object": "db.dataclasses.road_lane.RoadLane", "road_id": 61, "lane_num": 0}, {"py/object": "db.dataclasses.road_lane.RoadLane", "road_id": 22, "lane_num": 0}]}, {"py/tuple": [{"py/object": "db.dataclasses.road_lane.RoadLane", "road_id": 74, "lane_num": 0}, {"py/object": "db.dataclasses.road_lane.RoadLane", "road_id": 22, "lane_num": 0}]}], "traffic_lights": [[{"py/object": "db.dataclasses.road_lane.RoadLane", "road_id": 61, "lane_num": 0}], [{"py/object": "db.dataclasses.road_lane.RoadLane", "road_id": 74, "lane_num": 0}]], "traffic_lights_coords": [{"py/object": "server.geometry.point.Point", "_Point__x": 37.0, "_Point__y": 57.0}, {"py/object": "server.geometry.point.Point", "_Point__x": 43.0, "_Point__y": 57.0}], "num_traffic_lights": 2}, {"py/object": "db.dataclasses.junction_data.JunctionData", "idnum": 35, "coordinates": [{"py/object": "server.geometry.point.Point", "_Point__x": 98.71423, "_Point__y": 58.58929}, {"py/object": "server.geometry.point.Point", "_Point__x": 101.86561, "_Point__y": 59.14499}, {"py/object": "server.geometry.point.Point", "_Point__x": 100.70566, "_Point__y": 60.77426}, {"py/object": "server.geometry.point.Point", "_Point__x": 98.71423, "_Point__y": 60.5893}], "goes_to": [{"py/tuple": [{"py/object": "db.dataclasses.road_lane.RoadLane", "road_id": 12, "lane_num": 0}, {"py/object": "db.dataclasses.road_lane.RoadLane", "road_id": 92, "lane_num": 1}]}, {"py/tuple": [{"py/object": "db.dataclasses.road_lane.RoadLane", "road_id": 24, "lane_num": 0}, {"py/object": "db.dataclasses.road_lane.RoadLane", "road_id": 92, "lane_num": 1}]}, {"py/tuple": [{"py/object": "db.dataclasses.road_lane.RoadLane", "road_id": 79, "lane_num": 0}, {"py/object": "db.dataclasses.road_lane.RoadLane", "road_id": 92, "lane_num": 1}]}], "traffic_lights": [[{"py/object": "db.dataclasses.road_lane.RoadLane", "road_id": 12, "lane_num": 0}], [{"py/object": "db.dataclasses.road_lane.RoadLane", "road_id": 24, "lane_num": 0}], [{"py/object": "db.dataclasses.road_lane.RoadLane", "road_id": 79, "lane_num": 0}]], "traffic_lights_coords": [{"py/object": "server.geometry.point.Point", "_Point__x": 96.71423, "_Point__y": 62.5893}, {"py/object": "server.geometry.point.Point", "_Point__x": 102.70566, "_Point__y": 62.77426}, {"py/object": "server.geometry.point.Point", "_Point__x": 103.86561, "_Point__y": 57.14499}], "num_traffic_lights": 3}, {"py/object": "db.dataclasses.junction_data.JunctionData", "idnum": 36, "coordinates": [{"py/object": "server.geometry.point.Point", "_Point__x": 119.32541, "_Point__y": 58.67459}, {"py/object": "server.geometry.point.Point", "_Point__x": 121.32541, "_Point__y": 58.67459}, {"py/object": "server.geometry.point.Point", "_Point__x": 120.94241000000001, "_Point__y": 61.85159}, {"py/object": "server.geometry.point.Point", "_Point__x": 119.32541, "_Point__y": 60.6746}], "goes_to": [{"py/tuple": [{"py/object": "db.dataclasses.road_lane.RoadLane", "road_id": 6, "lane_num": 0}, {"py/object": "db.dataclasses.road_lane.RoadLane", "road_id": 85, "lane_num": 1}]}, {"py/tuple": [{"py/object": "db.dataclasses.road_lane.RoadLane", "road_id": 6, "lane_num": 1}, {"py/object": "db.dataclasses.road_lane.RoadLane", "road_id": 87, "lane_num": 0}]}, {"py/tuple": [{"py/object": "db.dataclasses.road_lane.RoadLane", "road_id": 6, "lane_num": 2}, {"py/object": "db.dataclasses.road_lane.RoadLane", "road_id": 79, "lane_num": 0}]}], "traffic_lights": [], "traffic_lights_coords": [], "num_traffic_lights": 0}, {"py/object": "db.dataclasses.junction_data.JunctionData", "idnum": 37, "coordinates": [{"py/object": "server.geometry.point.Point", "_Point__x": 139.04218, "_Point__y": 57.76463}, {"py/object": "server.geometry.point.Point", "_Point__x": 142.41278, "_Point__y": 60.59289}, {"py/object": "server.geometry.point.Point", "_Point__x": 140.49025, "_Point__y": 61.61488}, {"py/object": "server.geometry.point.Point", "_Point__x": 139.04218, "_Point__y": 60.23535}], "goes_to": [{"py/tuple": [{"py/object": "db.dataclasses.road_lane.RoadLane", "road_id": 84, "lane_num": 0}, {"py/object": "db.dataclasses.road_lane.RoadLane", "road_id": 20, "lane_num": 2}]}, {"py/tuple": [{"py/object": "db.dataclasses.road_lane.RoadLane", "road_id": 84, "lane_num": 1}, {"py/object": "db.dataclasses.road_lane.RoadLane", "road_id": 73, "lane_num": 0}]}, {"py/tuple": [{"py/object": "db.dataclasses.road_lane.RoadLane", "road_id": 85, "lane_num": 0}, {"py/object": "db.dataclasses.road_lane.RoadLane", "road_id": 20, "lane_num": 2}]}, {"py/tuple": [{"py/object": "db.dataclasses.road_lane.RoadLane", "road_id": 85, "lane_num": 1}, {"py/object": "db.dataclasses.road_lane.RoadLane", "road_id": 73, "lane_num": 0}]}], "traffic_lights": [[{"py/object": "db.dataclasses.road_lane.RoadLane", "road_id": 84, "lane_num": 0}, {"py/object": "db.dataclasses.road_lane.RoadLane", "road_id": 84, "lane_num": 1}], [{"py/object": "db.dataclasses.road_lane.RoadLane", "road_id": 85, "lane_num": 0}, {"py/object": "db.dataclasses.road_lane.RoadLane", "road_id": 85, "lane_num": 1}]], "traffic_lights_coords": [{"py/object": "server.geometry.point.Point", "_Point__x": 142.49025, "_Point__y": 63.61488}, {"py/object": "server.geometry.point.Point", "_Point__x": 137.04218, "_Point__y": 62.23535}], "num_traffic_lights": 2}, {"py/object": "db.dataclasses.junction_data.JunctionData", "idnum": 38, "coordinates": [{"py/object": "server.geometry.point.Point", "_Point__x": 158.67459, "_Point__y": 59.32541}, {"py/object": "server.geometry.point.Point", "_Point__x": 160.67459, "_Point__y": 59.32541}, {"py/object": "server.geometry.point.Point", "_Point__x": 161.85159, "_Point__y": 60.942429999999995}, {"py/object": "server.geometry.point.Point", "_Point__x": 158.67459, "_Point__y": 61.32541}], "goes_to": [{"py/tuple": [{"py/object": "db.dataclasses.road_lane.RoadLane", "road_id": 25, "lane_num": 0}, {"py/object": "db.dataclasses.road_lane.RoadLane", "road_id": 93, "lane_num": 1}]}, {"py/tuple": [{"py/object": "db.dataclasses.road_lane.RoadLane", "road_id": 44, "lane_num": 0}, {"py/object": "db.dataclasses.road_lane.RoadLane", "road_id": 93, "lane_num": 1}]}, {"py/tuple": [{"py/object": "db.dataclasses.road_lane.RoadLane", "road_id": 73, "lane_num": 0}, {"py/object": "db.dataclasses.road_lane.RoadLane", "road_id": 93, "lane_num": 1}]}], "traffic_lights": [[{"py/object": "db.dataclasses.road_lane.RoadLane", "road_id": 25, "lane_num": 0}], [{"py/object": "db.dataclasses.road_lane.RoadLane", "road_id": 44, "lane_num": 0}], [{"py/object": "db.dataclasses.road_lane.RoadLane", "road_id": 73, "lane_num": 0}]], "traffic_lights_coords": [{"py/object": "server.geometry.point.Point", "_Point__x": 156.67459, "_Point__y": 57.32541}, {"py/object": "server.geometry.point.Point", "_Point__x": 162.67459, "_Point__y": 57.32541}, {"py/object": "server.geometry.point.Point", "_Point__x": 156.67459, "_Point__y": 63.32541}], "num_traffic_lights": 3}, {"py/object": "db.dataclasses.junction_data.JunctionData", "idnum": 41, "coordinates": [{"py/object": "server.geometry.point.Point", "_Point__x": 19.0, "_Point__y": 79.0}, {"py/object": "server.geometry.point.Point", "_Point__x": 21.0, "_Point__y": 79.0}, {"py/object": "server.geometry.point.Point", "_Point__x": 21.0, "_Point__y": 81.0}, {"py/object": "server.geometry.point.Point", "_Point__x": 19.0, "_Point__y": 81.0}], "goes_to": [{"py/tuple": [{"py/object": "db.dataclasses.road_lane.RoadLane", "road_id": 0, "lane_num": 0}, {"py/object": "db.dataclasses.road_lane.RoadLane", "road_id": 34, "lane_num": 0}]}, {"py/tuple": [{"py/object": "db.dataclasses.road_lane.RoadLane", "road_id": 11, "lane_num": 0}, {"py/object": "db.dataclasses.road_lane.RoadLane", "road_id": 34, "lane_num": 0}]}, {"py/tuple": [{"py/object": "db.dataclasses.road_lane.RoadLane", "road_id": 57, "lane_num": 0}, {"py/object": "db.dataclasses.road_lane.RoadLane", "road_id": 34, "lane_num": 0}]}], "traffic_lights": [[{"py/object": "db.dataclasses.road_lane.RoadLane", "road_id": 0, "lane_num": 0}], [{"py/object": "db.dataclasses.road_lane.RoadLane", "road_id": 11, "lane_num": 0}], [{"py/object": "db.dataclasses.road_lane.RoadLane", "road_id": 57, "lane_num": 0}]], "traffic_lights_coords": [{"py/object": "server.geometry.point.Point", "_Point__x": 17.0, "_Point__y": 77.0}, {"py/object": "server.geometry.point.Point", "_Point__x": 23.0, "_Point__y": 83.0}, {"py/object": "server.geometry.point.Point", "_Point__x": 23.0, "_Point__y": 77.0}], "num_traffic_lights": 3}, {"py/object": "db.dataclasses.junction_data.JunctionData", "idnum": 42, "coordinates": [{"py/object": "server.geometry.point.Point", "_Point__x": 39.0, "_Point__y": 79.0}, {"py/object": "server.geometry.point.Point", "_Point__x": 41.0, "_Point__y": 79.0}, {"py/object": "server.geometry.point.Point", "_Point__x": 42.02978, "_Point__y": 82.02977}, {"py/object": "server.geometry.point.Point", "_Point__x": 39.0, "_Point__y": 81.0}], "goes_to": [{"py/tuple": [{"py/object": "db.dataclasses.road_lane.RoadLane", "road_id": 32, "lane_num": 0}, {"py/object": "db.dataclasses.road_lane.RoadLane", "road_id": 28, "lane_num": 1}]}, {"py/tuple": [{"py/object": "db.dataclasses.road_lane.RoadLane", "road_id": 32, "lane_num": 1}, {"py/object": "db.dataclasses.road_lane.RoadLane", "road_id": 59, "lane_num": 1}]}, {"py/tuple": [{"py/object": "db.dataclasses.road_lane.RoadLane", "road_id": 32, "lane_num": 2}, {"py/object": "db.dataclasses.road_lane.RoadLane", "road_id": 57, "lane_num": 0}]}], "traffic_lights": [], "traffic_lights_coords": [], "num_traffic_lights": 0}, {"py/object": "db.dataclasses.junction_data.JunctionData", "idnum": 43, "coordinates": [{"py/object": "server.geometry.point.Point", "_Point__x": 59.0, "_Point__y": 79.0}, {"py/object": "server.geometry.point.Point", "_Point__x": 61.0, "_Point__y": 79.0}, {"py/object": "server.geometry.point.Point", "_Point__x": 61.0, "_Point__y": 81.0}, {"py/object": "server.geometry.point.Point", "_Point__x": 59.0, "_Point__y": 81.0}], "goes_to": [{"py/tuple": [{"py/object": "db.dataclasses.road_lane.RoadLane", "road_id": 28, "lane_num": 0}, {"py/object": "db.dataclasses.road_lane.RoadLane", "road_id": 74, "lane_num": 0}]}, {"py/tuple": [{"py/object": "db.dataclasses.road_lane.RoadLane", "road_id": 28, "lane_num": 1}, {"py/object": "db.dataclasses.road_lane.RoadLane", "road_id": 96, "lane_num": 0}]}, {"py/tuple": [{"py/object": "db.dataclasses.road_lane.RoadLane", "road_id": 33, "lane_num": 0}, {"py/object": "db.dataclasses.road_lane.RoadLane", "road_id": 74, "lane_num": 0}]}, {"py/tuple": [{"py/object": "db.dataclasses.road_lane.RoadLane", "road_id": 33, "lane_num": 1}, {"py/object": "db.dataclasses.road_lane.RoadLane", "road_id": 96, "lane_num": 0}]}], "traffic_lights": [[{"py/object": "db.dataclasses.road_lane.RoadLane", "road_id": 28, "lane_num": 0}, {"py/object": "db.dataclasses.road_lane.RoadLane", "road_id": 28, "lane_num": 1}], [{"py/object": "db.dataclasses.road_lane.RoadLane", "road_id": 33, "lane_num": 0}, {"py/object": "db.dataclasses.road_lane.RoadLane", "road_id": 33, "lane_num": 1}]], "traffic_lights_coords": [{"py/object": "server.geometry.point.Point", "_Point__x": 57.0, "_Point__y": 83.0}, {"py/object": "server.geometry.point.Point", "_Point__x": 63.0, "_Point__y": 83.0}], "num_traffic_lights": 2}, {"py/object": "db.dataclasses.junction_data.JunctionData", "idnum": 44, "coordinates": [{"py/object": "server.geometry.point.Point", "_Point__x": 78.67459, "_Point__y": 79.32541}, {"py/object": "server.geometry.point.Point", "_Point__x": 80.67459, "_Point__y": 79.32541}, {"py/object": "server.geometry.point.Point", "_Point__x": 81.85159, "_Point__y": 80.94243}, {"py/object": "server.geometry.point.Point", "_Point__x": 78.67459, "_Point__y": 81.32541}], "goes_to": [{"py/tuple": [{"py/object": "db.dataclasses.road_lane.RoadLane", "road_id": 45, "lane_num": 0}, {"py/object": "db.dataclasses.road_lane.RoadLane", "road_id": 33, "lane_num": 1}]}, {"py/tuple": [{"py/object": "db.dataclasses.road_lane.RoadLane", "road_id": 96, "lane_num": 0}, {"py/object": "db.dataclasses.road_lane.RoadLane", "road_id": 33, "lane_num": 1}]}], "traffic_lights": [[{"py/object": "db.dataclasses.road_lane.RoadLane", "road_id": 45, "lane_num": 0}], [{"py/object": "db.dataclasses.road_lane.RoadLane", "road_id": 96, "lane_num": 0}]], "traffic_lights_coords": [{"py/object": "server.geometry.point.Point", "_Point__x": 76.67459, "_Point__y": 77.32541}, {"py/object": "server.geometry.point.Point", "_Point__x": 76.67459, "_Point__y": 83.32541}], "num_traffic_lights": 2}, {"py/object": "db.dataclasses.junction_data.JunctionData", "idnum": 45, "coordinates": [{"py/object": "server.geometry.point.Point", "_Point__x": 99.0, "_Point__y": 79.0}, {"py/object": "server.geometry.point.Point", "_Point__x": 101.0, "_Point__y": 79.0}, {"py/object": "server.geometry.point.Point", "_Point__x": 101.0, "_Point__y": 81.0}, {"py/object": "server.geometry.point.Point", "_Point__x": 99.0, "_Point__y": 81.0}], "goes_to": [{"py/tuple": [{"py/object": "db.dataclasses.road_lane.RoadLane", "road_id": 51, "lane_num": 0}, {"py/object": "db.dataclasses.road_lane.RoadLane", "road_id": 24, "lane_num": 0}]}, {"py/tuple": [{"py/object": "db.dataclasses.road_lane.RoadLane", "road_id": 87, "lane_num": 0}, {"py/object": "db.dataclasses.road_lane.RoadLane", "road_id": 24, "lane_num": 0}]}], "traffic_lights": [[{"py/object": "db.dataclasses.road_lane.RoadLane", "road_id": 51, "lane_num": 0}], [{"py/object": "db.dataclasses.road_lane.RoadLane", "road_id": 87, "lane_num": 0}]], "traffic_lights_coords": [{"py/object": "server.geometry.point.Point", "_Point__x": 103.0, "_Point__y": 83.0}, {"py/object": "server.geometry.point.Point", "_Point__x": 103.0, "_Point__y": 77.0}], "num_traffic_lights": 2}, {"py/object": "db.dataclasses.junction_data.JunctionData", "idnum": 46, "coordinates": [{"py/object": "server.geometry.point.Point", "_Point__x": 119.0, "_Point__y": 78.4}, {"py/object": "server.geometry.point.Point", "_Point__x": 121.0, "_Point__y": 78.4}, {"py/object": "server.geometry.point.Point", "_Point__x": 121.0, "_Point__y": 81.6}, {"py/object": "server.geometry.point.Point", "_Point__x": 119.0, "_Point__y": 81.6}], "goes_to": [{"py/tuple": [{"py/object": "db.dataclasses.road_lane.RoadLane", "road_id": 17, "lane_num": 0}, {"py/object": "db.dataclasses.road_lane.RoadLane", "road_id": 69, "lane_num": 1}]}, {"py/tuple": [{"py/object": "db.dataclasses.road_lane.RoadLane", "road_id": 17, "lane_num": 1}, {"py/object": "db.dataclasses.road_lane.RoadLane", "road_id": 43, "lane_num": 1}]}], "traffic_lights": [], "traffic_lights_coords": [], "num_traffic_lights": 0}, {"py/object": "db.dataclasses.junction_data.JunctionData", "idnum": 48, "coordinates": [{"py/object": "server.geometry.point.Point", "_Point__x": 158.83399, "_Point__y": 78.4888}, {"py/object": "server.geometry.point.Point", "_Point__x": 160.8036, "_Point__y": 78.83613}, {"py/object": "server.geometry.point.Point", "_Point__x": 160.63993, "_Point__y": 80.82938}, {"py/object": "server.geometry.point.Point", "_Point__x": 158.83399, "_Point__y": 81.68879}], "goes_to": [{"py/tuple": [{"py/object": "db.dataclasses.road_lane.RoadLane", "road_id": 9, "lane_num": 0}, {"py/object": "db.dataclasses.road_lane.RoadLane", "road_id": 84, "lane_num": 1}]}, {"py/tuple": [{"py/object": "db.dataclasses.road_lane.RoadLane", "road_id": 9, "lane_num": 1}, {"py/object": "db.dataclasses.road_lane.RoadLane", "road_id": 54, "lane_num": 0}]}, {"py/tuple": [{"py/object": "db.dataclasses.road_lane.RoadLane", "road_id": 93, "lane_num": 0}, {"py/object": "db.dataclasses.road_lane.RoadLane", "road_id": 54, "lane_num": 0}]}, {"py/tuple": [{"py/object": "db.dataclasses.road_lane.RoadLane", "road_id": 93, "lane_num": 1}, {"py/object": "db.dataclasses.road_lane.RoadLane", "road_id": 84, "lane_num": 1}]}], "traffic_lights": [[{"py/object": "db.dataclasses.road_lane.RoadLane", "road_id": 9, "lane_num": 0}, {"py/object": "db.dataclasses.road_lane.RoadLane", "road_id": 9, "lane_num": 1}], [{"py/object": "db.dataclasses.road_lane.RoadLane", "road_id": 93, "lane_num": 0}, {"py/object": "db.dataclasses.road_lane.RoadLane", "road_id": 93, "lane_num": 1}]], "traffic_lights_coords": [{"py/object": "server.geometry.point.Point", "_Point__x": 162.63993, "_Point__y": 82.82938}, {"py/object": "server.geometry.point.Point", "_Point__x": 156.83399, "_Point__y": 76.4888}], "num_traffic_lights": 2}, {"py/object": "db.dataclasses.junction_data.JunctionData", "idnum": 50, "coordinates": [{"py/object": "server.geometry.point.Point", "_Point__x": -0.67459, "_Point__y": 98.67459}, {"py/object": "server.geometry.point.Point", "_Point__x": 1.32541, "_Point__y": 98.67459}, {"py/object": "server.geometry.point.Point", "_Point__x": 0.94241, "_Point__y": 101.85159}, {"py/object": "server.geometry.point.Point", "_Point__x": -0.67459, "_Point__y": 100.6746}], "goes_to": [{"py/tuple": [{"py/object": "db.dataclasses.road_lane.RoadLane", "road_id": 34, "lane_num": 0}, {"py/object": "db.dataclasses.road_lane.RoadLane", "road_id": 72, "lane_num": 1}]}, {"py/tuple": [{"py/object": "db.dataclasses.road_lane.RoadLane", "road_id": 36, "lane_num": 0}, {"py/object": "db.dataclasses.road_lane.RoadLane", "road_id": 72, "lane_num": 1}]}], "traffic_lights": [[{"py/object": "db.dataclasses.road_lane.RoadLane", "road_id": 34, "lane_num": 0}], [{"py/object": "db.dataclasses.road_lane.RoadLane", "road_id": 36, "lane_num": 0}]], "traffic_lights_coords": [{"py/object": "server.geometry.point.Point", "_Point__x": -2.6745900000000002, "_Point__y": 96.67459}, {"py/object": "server.geometry.point.Point", "_Point__x": 2.9424099999999997, "_Point__y": 103.85159}], "num_traffic_lights": 2}, {"py/object": "db.dataclasses.junction_data.JunctionData", "idnum": 51, "coordinates": [{"py/object": "server.geometry.point.Point", "_Point__x": 19.0, "_Point__y": 99.0}, {"py/object": "server.geometry.point.Point", "_Point__x": 21.0, "_Point__y": 99.0}, {"py/object": "server.geometry.point.Point", "_Point__x": 21.0, "_Point__y": 101.0}, {"py/object": "server.geometry.point.Point", "_Point__x": 19.0, "_Point__y": 101.0}], "goes_to": [{"py/tuple": [{"py/object": "db.dataclasses.road_lane.RoadLane", "road_id": 59, "lane_num": 0}, {"py/object": "db.dataclasses.road_lane.RoadLane", "road_id": 35, "lane_num": 0}]}, {"py/tuple": [{"py/object": "db.dataclasses.road_lane.RoadLane", "road_id": 59, "lane_num": 1}, {"py/object": "db.dataclasses.road_lane.RoadLane", "road_id": 11, "lane_num": 0}]}, {"py/tuple": [{"py/object": "db.dataclasses.road_lane.RoadLane", "road_id": 72, "lane_num": 0}, {"py/object": "db.dataclasses.road_lane.RoadLane", "road_id": 11, "lane_num": 0}]}, {"py/tuple": [{"py/object": "db.dataclasses.road_lane.RoadLane", "road_id": 72, "lane_num": 1}, {"py/object": "db.dataclasses.road_lane.RoadLane", "road_id": 35, "lane_num": 0}]}], "traffic_lights": [[{"py/object": "db.dataclasses.road_lane.RoadLane", "road_id": 59, "lane_num": 0}, {"py/object": "db.dataclasses.road_lane.RoadLane", "road_id": 59, "lane_num": 1}], [{"py/object": "db.dataclasses.road_lane.RoadLane", "road_id": 72, "lane_num": 0}, {"py/object": "db.dataclasses.road_lane.RoadLane", "road_id": 72, "lane_num": 1}]], "traffic_lights_coords": [{"py/object": "server.geometry.point.Point", "_Point__x": 23.0, "_Point__y": 97.0}, {"py/object": "server.geometry.point.Point", "_Point__x": 17.0, "_Point__y": 103.0}], "num_traffic_lights": 2}, {"py/object": "db.dataclasses.junction_data.JunctionData", "idnum": 55, "coordinates": [{"py/object": "server.geometry.point.Point", "_Point__x": 98.75697, "_Point__y": 99.847}, {"py/object": "server.geometry.point.Point", "_Point__x": 100.48902, "_Point__y": 98.847}, {"py/object": "server.geometry.point.Point", "_Point__x": 102.41187, "_Point__y": 99.70315000000001}, {"py/object": "server.geometry.point.Point", "_Point__x": 98.75697, "_Point__y": 102.15299}], "goes_to": [{"py/tuple": [{"py/object": "db.dataclasses.road_lane.RoadLane", "road_id": 69, "lane_num": 0}, {"py/object": "db.dataclasses.road_lane.RoadLane", "road_id": 10, "lane_num": 0}]}, {"py/tuple": [{"py/object": "db.dataclasses.road_lane.RoadLane", "road_id": 69, "lane_num": 1}, {"py/object": "db.dataclasses.road_lane.RoadLane", "road_id": 63, "lane_num": 2}]}], "traffic_lights": [], "traffic_lights_coords": [], "num_traffic_lights": 0}, {"py/object": "db.dataclasses.junction_data.JunctionData", "idnum": 57, "coordinates": [{"py/object": "server.geometry.point.Point", "_Point__x": 139.32541, "_Point__y": 98.67459}, {"py/object": "server.geometry.point.Point", "_Point__x": 141.32541, "_Point__y": 98.67459}, {"py/object": "server.geometry.point.Point", "_Point__x": 140.94241, "_Point__y": 101.85159}, {"py/object": "server.geometry.point.Point", "_Point__x": 139.32541, "_Point__y": 100.6746}], "goes_to": [{"py/tuple": [{"py/object": "db.dataclasses.road_lane.RoadLane", "road_id": 43, "lane_num": 0}, {"py/object": "db.dataclasses.road_lane.RoadLane", "road_id": 9, "lane_num": 1}]}, {"py/tuple": [{"py/object": "db.dataclasses.road_lane.RoadLane", "road_id": 43, "lane_num": 1}, {"py/object": "db.dataclasses.road_lane.RoadLane", "road_id": 53, "lane_num": 0}]}], "traffic_lights": [], "traffic_lights_coords": [], "num_traffic_lights": 0}, {"py/object": "db.dataclasses.junction_data.JunctionData", "idnum": 59, "coordinates": [{"py/object": "server.geometry.point.Point", "_Point__x": 179.0, "_Point__y": 99.0}, {"py/object": "server.geometry.point.Point", "_Point__x": 181.0, "_Point__y": 99.0}, {"py/object": "server.geometry.point.Point", "_Point__x": 181.0, "_Point__y": 101.0}, {"py/object": "server.geometry.point.Point", "_Point__x": 179.0, "_Point__y": 101.0}], "goes_to": [{"py/tuple": [{"py/object": "db.dataclasses.road_lane.RoadLane", "road_id": 54, "lane_num": 0}, {"py/object": "db.dataclasses.road_lane.RoadLane", "road_id": 56, "lane_num": 0}]}, {"py/tuple": [{"py/object": "db.dataclasses.road_lane.RoadLane", "road_id": 71, "lane_num": 0}, {"py/object": "db.dataclasses.road_lane.RoadLane", "road_id": 56, "lane_num": 0}]}], "traffic_lights": [[{"py/object": "db.dataclasses.road_lane.RoadLane", "road_id": 54, "lane_num": 0}], [{"py/object": "db.dataclasses.road_lane.RoadLane", "road_id": 71, "lane_num": 0}]], "traffic_lights_coords": [{"py/object": "server.geometry.point.Point", "_Point__x": 177.0, "_Point__y": 97.0}, {"py/object": "server.geometry.point.Point", "_Point__x": 183.0, "_Point__y": 103.0}], "num_traffic_lights": 2}, {"py/object": "db.dataclasses.junction_data.JunctionData", "idnum": 61, "coordinates": [{"py/object": "server.geometry.point.Point", "_Point__x": 19.32541, "_Point__y": 118.67459}, {"py/object": "server.geometry.point.Point", "_Point__x": 21.32541, "_Point__y": 118.67459}, {"py/object": "server.geometry.point.Point", "_Point__x": 20.942410000000002, "_Point__y": 121.85159}, {"py/object": "server.geometry.point.Point", "_Point__x": 19.32541, "_Point__y": 120.6746}], "goes_to": [{"py/tuple": [{"py/object": "db.dataclasses.road_lane.RoadLane", "road_id": 16, "lane_num": 0}, {"py/object": "db.dataclasses.road_lane.RoadLane", "road_id": 47, "lane_num": 1}]}, {"py/tuple": [{"py/object": "db.dataclasses.road_lane.RoadLane", "road_id": 35, "lane_num": 0}, {"py/object": "db.dataclasses.road_lane.RoadLane", "road_id": 47, "lane_num": 1}]}], "traffic_lights": [[{"py/object": "db.dataclasses.road_lane.RoadLane", "road_id": 16, "lane_num": 0}], [{"py/object": "db.dataclasses.road_lane.RoadLane", "road_id": 35, "lane_num": 0}]], "traffic_lights_coords": [{"py/object": "server.geometry.point.Point", "_Point__x": 22.942410000000002, "_Point__y": 123.85159}, {"py/object": "server.geometry.point.Point", "_Point__x": 17.32541, "_Point__y": 116.67459}], "num_traffic_lights": 2}, {"py/object": "db.dataclasses.junction_data.JunctionData", "idnum": 63, "coordinates": [{"py/object": "server.geometry.point.Point", "_Point__x": 59.0, "_Point__y": 119.0}, {"py/object": "server.geometry.point.Point", "_Point__x": 61.0, "_Point__y": 119.0}, {"py/object": "server.geometry.point.Point", "_Point__x": 61.0, "_Point__y": 121.0}, {"py/object": "server.geometry.point.Point", "_Point__x": 59.0, "_Point__y": 121.0}], "goes_to": [{"py/tuple": [{"py/object": "db.dataclasses.road_lane.RoadLane", "road_id": 47, "lane_num": 0}, {"py/object": "db.dataclasses.road_lane.RoadLane", "road_id": 48, "lane_num": 0}]}, {"py/tuple": [{"py/object": "db.dataclasses.road_lane.RoadLane", "road_id": 47, "lane_num": 1}, {"py/object": "db.dataclasses.road_lane.RoadLane", "road_id": 16, "lane_num": 0}]}, {"py/tuple": [{"py/object": "db.dataclasses.road_lane.RoadLane", "road_id": 91, "lane_num": 0}, {"py/object": "db.dataclasses.road_lane.RoadLane", "road_id": 16, "lane_num": 0}]}, {"py/tuple": [{"py/object": "db.dataclasses.road_lane.RoadLane", "road_id": 91, "lane_num": 1}, {"py/object": "db.dataclasses.road_lane.RoadLane", "road_id": 48, "lane_num": 0}]}], "traffic_lights": [[{"py/object": "db.dataclasses.road_lane.RoadLane", "road_id": 47, "lane_num": 0}, {"py/object": "db.dataclasses.road_lane.RoadLane", "road_id": 47, "lane_num": 1}], [{"py/object": "db.dataclasses.road_lane.RoadLane", "road_id": 91, "lane_num": 0}, {"py/object": "db.dataclasses.road_lane.RoadLane", "road_id": 91, "lane_num": 1}]], "traffic_lights_coords": [{"py/object": "server.geometry.point.Point", "_Point__x": 57.0, "_Point__y": 117.0}, {"py/object": "server.geometry.point.Point", "_Point__x": 63.0, "_Point__y": 123.0}], "num_traffic_lights": 2}, {"py/object": "db.dataclasses.junction_data.JunctionData", "idnum": 64, "coordinates": [{"py/object": "server.geometry.point.Point", "_Point__x": 79.0, "_Point__y": 119.0}, {"py/object": "server.geometry.point.Point", "_Point__x": 81.0, "_Point__y": 119.0}, {"py/object": "server.geometry.point.Point", "_Point__x": 81.0, "_Point__y": 121.0}, {"py/object": "server.geometry.point.Point", "_Point__x": 79.0, "_Point__y": 121.0}], "goes_to": [{"py/tuple": [{"py/object": "db.dataclasses.road_lane.RoadLane", "road_id": 23, "lane_num": 0}, {"py/object": "db.dataclasses.road_lane.RoadLane", "road_id": 51, "lane_num": 0}]}, {"py/tuple": [{"py/object": "db.dataclasses.road_lane.RoadLane", "road_id": 48, "lane_num": 0}, {"py/object": "db.dataclasses.road_lane.RoadLane", "road_id": 51, "lane_num": 0}]}, {"py/tuple": [{"py/object": "db.dataclasses.road_lane.RoadLane", "road_id": 100, "lane_num": 0}, {"py/object": "db.dataclasses.road_lane.RoadLane", "road_id": 51, "lane_num": 0}]}], "traffic_lights": [[{"py/object": "db.dataclasses.road_lane.RoadLane", "road_id": 23, "lane_num": 0}], [{"py/object": "db.dataclasses.road_lane.RoadLane", "road_id": 48, "lane_num": 0}], [{"py/object": "db.dataclasses.road_lane.RoadLane", "road_id": 100, "lane_num": 0}]], "traffic_lights_coords": [{"py/object": "server.geometry.point.Point", "_Point__x": 83.0, "_Point__y": 117.0}, {"py/object": "server.geometry.point.Point", "_Point__x": 77.0, "_Point__y": 123.0}, {"py/object": "server.geometry.point.Point", "_Point__x": 83.0, "_Point__y": 123.0}], "num_traffic_lights": 3}, {"py/object": "db.dataclasses.junction_data.JunctionData", "idnum": 65, "coordinates": [{"py/object": "server.geometry.point.Point", "_Point__x": 99.0, "_Point__y": 119.0}, {"py/object": "server.geometry.point.Point", "_Point__x": 101.0, "_Point__y": 119.0}, {"py/object": "server.geometry.point.Point", "_Point__x": 101.0, "_Point__y": 121.0}, {"py/object": "server.geometry.point.Point", "_Point__x": 99.0, "_Point__y": 121.0}], "goes_to": [{"py/tuple": [{"py/object": "db.dataclasses.road_lane.RoadLane", "road_id": 63, "lane_num": 0}, {"py/object": "db.dataclasses.road_lane.RoadLane", "road_id": 1, "lane_num": 0}]}, {"py/tuple": [{"py/object": "db.dataclasses.road_lane.RoadLane", "road_id": 63, "lane_num": 1}, {"py/object": "db.dataclasses.road_lane.RoadLane", "road_id": 78, "lane_num": 0}]}, {"py/tuple": [{"py/object": "db.dataclasses.road_lane.RoadLane", "road_id": 63, "lane_num": 2}, {"py/object": "db.dataclasses.road_lane.RoadLane", "road_id": 23, "lane_num": 0}]}], "traffic_lights": [], "traffic_lights_coords": [], "num_traffic_lights": 0}, {"py/object": "db.dataclasses.junction_data.JunctionData", "idnum": 66, "coordinates": [{"py/object": "server.geometry.point.Point", "_Point__x": 119.32541, "_Point__y": 118.67459}, {"py/object": "server.geometry.point.Point", "_Point__x": 121.32541, "_Point__y": 118.67459}, {"py/object": "server.geometry.point.Point", "_Point__x": 120.94241000000001, "_Point__y": 121.85159}, {"py/object": "server.geometry.point.Point", "_Point__x": 119.32541, "_Point__y": 120.6746}], "goes_to": [{"py/tuple": [{"py/object": "db.dataclasses.road_lane.RoadLane", "road_id": 1, "lane_num": 0}, {"py/object": "db.dataclasses.road_lane.RoadLane", "road_id": 66, "lane_num": 1}]}, {"py/tuple": [{"py/object": "db.dataclasses.road_lane.RoadLane", "road_id": 10, "lane_num": 0}, {"py/object": "db.dataclasses.road_lane.RoadLane", "road_id": 66, "lane_num": 1}]}, {"py/tuple": [{"py/object": "db.dataclasses.road_lane.RoadLane", "road_id": 75, "lane_num": 0}, {"py/object": "db.dataclasses.road_lane.RoadLane", "road_id": 66, "lane_num": 1}]}], "traffic_lights": [[{"py/object": "db.dataclasses.road_lane.RoadLane", "road_id": 1, "lane_num": 0}], [{"py/object": "db.dataclasses.road_lane.RoadLane", "road_id": 10, "lane_num": 0}], [{"py/object": "db.dataclasses.road_lane.RoadLane", "road_id": 75, "lane_num": 0}]], "traffic_lights_coords": [{"py/object": "server.geometry.point.Point", "_Point__x": 117.32541, "_Point__y": 122.6746}, {"py/object": "server.geometry.point.Point", "_Point__x": 117.32541, "_Point__y": 116.67459}, {"py/object": "server.geometry.point.Point", "_Point__x": 122.94241000000001, "_Point__y": 123.85159}], "num_traffic_lights": 3}, {"py/object": "db.dataclasses.junction_data.JunctionData", "idnum": 67, "coordinates": [{"py/object": "server.geometry.point.Point", "_Point__x": 138.71423, "_Point__y": 118.58929}, {"py/object": "server.geometry.point.Point", "_Point__x": 141.86560999999998, "_Point__y": 119.14499}, {"py/object": "server.geometry.point.Point", "_Point__x": 140.70566, "_Point__y": 120.77426}, {"py/object": "server.geometry.point.Point", "_Point__x": 138.71423, "_Point__y": 120.5893}], "goes_to": [{"py/tuple": [{"py/object": "db.dataclasses.road_lane.RoadLane", "road_id": 66, "lane_num": 0}, {"py/object": "db.dataclasses.road_lane.RoadLane", "road_id": 17, "lane_num": 1}]}, {"py/tuple": [{"py/object": "db.dataclasses.road_lane.RoadLane", "road_id": 66, "lane_num": 1}, {"py/object": "db.dataclasses.road_lane.RoadLane", "road_id": 95, "lane_num": 0}]}], "traffic_lights": [], "traffic_lights_coords": [], "num_traffic_lights": 0}, {"py/object": "db.dataclasses.junction_data.JunctionData", "idnum": 68, "coordinates": [{"py/object": "server.geometry.point.Point", "_Point__x": 159.32541, "_Point__y": 118.67459}, {"py/object": "server.geometry.point.Point", "_Point__x": 161.32541, "_Point__y": 118.67459}, {"py/object": "server.geometry.point.Point", "_Point__x": 160.94241, "_Point__y": 121.85159}, {"py/object": "server.geometry.point.Point", "_Point__x": 159.32541, "_Point__y": 120.6746}], "goes_to": [{"py/tuple": [{"py/object": "db.dataclasses.road_lane.RoadLane", "road_id": 53, "lane_num": 0}, {"py/object": "db.dataclasses.road_lane.RoadLane", "road_id": 3, "lane_num": 1}]}, {"py/tuple": [{"py/object": "db.dataclasses.road_lane.RoadLane", "road_id": 56, "lane_num": 0}, {"py/object": "db.dataclasses.road_lane.RoadLane", "road_id": 3, "lane_num": 1}]}, {"py/tuple": [{"py/object": "db.dataclasses.road_lane.RoadLane", "road_id": 95, "lane_num": 0}, {"py/object": "db.dataclasses.road_lane.RoadLane", "road_id": 3, "lane_num": 1}]}], "traffic_lights": [[{"py/object": "db.dataclasses.road_lane.RoadLane", "road_id": 53, "lane_num": 0}], [{"py/object": "db.dataclasses.road_lane.RoadLane", "road_id": 56, "lane_num": 0}], [{"py/object": "db.dataclasses.road_lane.RoadLane", "road_id": 95, "lane_num": 0}]], "traffic_lights_coords": [{"py/object": "server.geometry.point.Point", "_Point__x": 157.32541, "_Point__y": 122.6746}, {"py/object": "server.geometry.point.Point", "_Point__x": 157.32541, "_Point__y": 116.67459}, {"py/object": "server.geometry.point.Point", "_Point__x": 162.94241, "_Point__y": 123.85159}], "num_traffic_lights": 3}, {"py/object": "db.dataclasses.junction_data.JunctionData", "idnum": 69, "coordinates": [{"py/object": "server.geometry.point.Point", "_Point__x": 179.0, "_Point__y": 119.0}, {"py/object": "server.geometry.point.Point", "_Point__x": 181.0, "_Point__y": 119.0}, {"py/object": "server.geometry.point.Point", "_Point__x": 181.0, "_Point__y": 121.0}, {"py/object": "server.geometry.point.Point", "_Point__x": 179.0, "_Point__y": 121.0}], "goes_to": [{"py/tuple": [{"py/object": "db.dataclasses.road_lane.RoadLane", "road_id": 3, "lane_num": 0}, {"py/object": "db.dataclasses.road_lane.RoadLane", "road_id": 71, "lane_num": 0}]}, {"py/tuple": [{"py/object": "db.dataclasses.road_lane.RoadLane", "road_id": 3, "lane_num": 1}, {"py/object": "db.dataclasses.road_lane.RoadLane", "road_id": 52, "lane_num": 0}]}], "traffic_lights": [], "traffic_lights_coords": [], "num_traffic_lights": 0}, {"py/object": "db.dataclasses.junction_data.JunctionData", "idnum": 73, "coordinates": [{"py/object": "server.geometry.point.Point", "_Point__x": 58.71423, "_Point__y": 138.58929}, {"py/object": "server.geometry.point.Point", "_Point__x": 61.865610000000004, "_Point__y": 139.14499}, {"py/object": "server.geometry.point.Point", "_Point__x": 60.70566, "_Point__y": 140.77426}, {"py/object": "server.geometry.point.Point", "_Point__x": 58.71423, "_Point__y": 140.5893}], "goes_to": [{"py/tuple": [{"py/object": "db.dataclasses.road_lane.RoadLane", "road_id": 76, "lane_num": 0}, {"py/object": "db.dataclasses.road_lane.RoadLane", "road_id": 91, "lane_num": 1}]}, {"py/tuple": [{"py/object": "db.dataclasses.road_lane.RoadLane", "road_id": 76, "lane_num": 1}, {"py/object": "db.dataclasses.road_lane.RoadLane", "road_id": 100, "lane_num": 0}]}], "traffic_lights": [], "traffic_lights_coords": [], "num_traffic_lights": 0}, {"py/object": "db.dataclasses.junction_data.JunctionData", "idnum": 74, "coordinates": [{"py/object": "server.geometry.point.Point", "_Point__x": 79.0, "_Point__y": 139.0}, {"py/object": "server.geometry.point.Point", "_Point__x": 81.0, "_Point__y": 139.0}, {"py/object": "server.geometry.point.Point", "_Point__x": 81.0, "_Point__y": 141.0}, {"py/object": "server.geometry.point.Point", "_Point__x": 79.0, "_Point__y": 141.0}], "goes_to": [{"py/tuple": [{"py/object": "db.dataclasses.road_lane.RoadLane", "road_id": 5, "lane_num": 0}, {"py/object": "db.dataclasses.road_lane.RoadLane", "road_id": 13, "lane_num": 0}]}, {"py/tuple": [{"py/object": "db.dataclasses.road_lane.RoadLane", "road_id": 39, "lane_num": 0}, {"py/object": "db.dataclasses.road_lane.RoadLane", "road_id": 13, "lane_num": 0}]}], "traffic_lights": [[{"py/object": "db.dataclasses.road_lane.RoadLane", "road_id": 5, "lane_num": 0}], [{"py/object": "db.dataclasses.road_lane.RoadLane", "road_id": 39, "lane_num": 0}]], "traffic_lights_coords": [{"py/object": "server.geometry.point.Point", "_Point__x": 77.0, "_Point__y": 143.0}, {"py/object": "server.geometry.point.Point", "_Point__x": 83.0, "_Point__y": 143.0}], "num_traffic_lights": 2}, {"py/object": "db.dataclasses.junction_data.JunctionData", "idnum": 75, "coordinates": [{"py/object": "server.geometry.point.Point", "_Point__x": 99.51098, "_Point__y": 138.84701}, {"py/object": "server.geometry.point.Point", "_Point__x": 101.24303, "_Point__y": 137.84701}, {"py/object": "server.geometry.point.Point", "_Point__x": 100.94885000000001, "_Point__y": 142.23716000000002}, {"py/object": "server.geometry.point.Point", "_Point__x": 99.51098, "_Point__y": 140.84701}], "goes_to": [{"py/tuple": [{"py/object": "db.dataclasses.road_lane.RoadLane", "road_id": 13, "lane_num": 0}, {"py/object": "db.dataclasses.road_lane.RoadLane", "road_id": 21, "lane_num": 2}]}, {"py/tuple": [{"py/object": "db.dataclasses.road_lane.RoadLane", "road_id": 14, "lane_num": 0}, {"py/object": "db.dataclasses.road_lane.RoadLane", "road_id": 21, "lane_num": 2}]}, {"py/tuple": [{"py/object": "db.dataclasses.road_lane.RoadLane", "road_id": 78, "lane_num": 0}, {"py/object": "db.dataclasses.road_lane.RoadLane", "road_id": 21, "lane_num": 2}]}], "traffic_lights": [[{"py/object": "db.dataclasses.road_lane.RoadLane", "road_id": 13, "lane_num": 0}], [{"py/object": "db.dataclasses.road_lane.RoadLane", "road_id": 14, "lane_num": 0}], [{"py/object": "db.dataclasses.road_lane.RoadLane", "road_id": 78, "lane_num": 0}]], "traffic_lights_coords": [{"py/object": "server.geometry.point.Point", "_Point__x": 97.51098, "_Point__y": 142.84701}, {"py/object": "server.geometry.point.Point", "_Point__x": 102.94885000000001, "_Point__y": 144.23716000000002}, {"py/object": "server.geometry.point.Point", "_Point__x": 97.51098, "_Point__y": 136.84701}], "num_traffic_lights": 3}, {"py/object": "db.dataclasses.junction_data.JunctionData", "idnum": 76, "coordinates": [{"py/object": "server.geometry.point.Point", "_Point__x": 118.75697, "_Point__y": 139.847}, {"py/object": "server.geometry.point.Point", "_Point__x": 120.48902, "_Point__y": 138.847}, {"py/object": "server.geometry.point.Point", "_Point__x": 122.41187, "_Point__y": 139.70315}, {"py/object": "server.geometry.point.Point", "_Point__x": 118.75697, "_Point__y": 142.15299}], "goes_to": [{"py/tuple": [{"py/object": "db.dataclasses.road_lane.RoadLane", "road_id": 21, "lane_num": 0}, {"py/object": "db.dataclasses.road_lane.RoadLane", "road_id": 75, "lane_num": 0}]}, {"py/tuple": [{"py/object": "db.dataclasses.road_lane.RoadLane", "road_id": 21, "lane_num": 1}, {"py/object": "db.dataclasses.road_lane.RoadLane", "road_id": 68, "lane_num": 0}]}, {"py/tuple": [{"py/object": "db.dataclasses.road_lane.RoadLane", "road_id": 21, "lane_num": 2}, {"py/object": "db.dataclasses.road_lane.RoadLane", "road_id": 26, "lane_num": 2}]}], "traffic_lights": [], "traffic_lights_coords": [], "num_traffic_lights": 0}, {"py/object": "db.dataclasses.junction_data.JunctionData", "idnum": 79, "coordinates": [{"py/object": "server.geometry.point.Point", "_Point__x": 178.67459, "_Point__y": 139.32541}, {"py/object": "server.geometry.point.Point", "_Point__x": 180.67459, "_Point__y": 139.32541}, {"py/object": "server.geometry.point.Point", "_Point__x": 181.85159, "_Point__y": 140.94243}, {"py/object": "server.geometry.point.Point", "_Point__x": 178.67459, "_Point__y": 141.32541}], "goes_to": [{"py/tuple": [{"py/object": "db.dataclasses.road_lane.RoadLane", "road_id": 52, "lane_num": 0}, {"py/object": "db.dataclasses.road_lane.RoadLane", "road_id": 86, "lane_num": 1}]}, {"py/tuple": [{"py/object": "db.dataclasses.road_lane.RoadLane", "road_id": 77, "lane_num": 0}, {"py/object": "db.dataclasses.road_lane.RoadLane", "road_id": 86, "lane_num": 1}]}], "traffic_lights": [[{"py/object": "db.dataclasses.road_lane.RoadLane", "road_id": 52, "lane_num": 0}], [{"py/object": "db.dataclasses.road_lane.RoadLane", "road_id": 77, "lane_num": 0}]], "traffic_lights_coords": [{"py/object": "server.geometry.point.Point", "_Point__x": 176.67459, "_Point__y": 137.32541}, {"py/object": "server.geometry.point.Point", "_Point__x": 176.67459, "_Point__y": 143.32541}], "num_traffic_lights": 2}, {"py/object": "db.dataclasses.junction_data.JunctionData", "idnum": 81, "coordinates": [{"py/object": "server.geometry.point.Point", "_Point__x": 18.83399, "_Point__y": 158.4888}, {"py/object": "server.geometry.point.Point", "_Point__x": 20.8036, "_Point__y": 158.83613}, {"py/object": "server.geometry.point.Point", "_Point__x": 20.63993, "_Point__y": 160.82938000000001}, {"py/object": "server.geometry.point.Point", "_Point__x": 18.83399, "_Point__y": 161.68879}], "goes_to": [{"py/tuple": [{"py/object": "db.dataclasses.road_lane.RoadLane", "road_id": 42, "lane_num": 0}, {"py/object": "db.dataclasses.road_lane.RoadLane", "road_id": 55, "lane_num": 1}]}, {"py/tuple": [{"py/object": "db.dataclasses.road_lane.RoadLane", "road_id": 42, "lane_num": 1}, {"py/object": "db.dataclasses.road_lane.RoadLane", "road_id": 36, "lane_num": 0}]}, {"py/tuple": [{"py/object": "db.dataclasses.road_lane.RoadLane", "road_id": 88, "lane_num": 0}, {"py/object": "db.dataclasses.road_lane.RoadLane", "road_id": 55, "lane_num": 1}]}, {"py/tuple": [{"py/object": "db.dataclasses.road_lane.RoadLane", "road_id": 88, "lane_num": 1}, {"py/object": "db.dataclasses.road_lane.RoadLane", "road_id": 36, "lane_num": 0}]}], "traffic_lights": [[{"py/object": "db.dataclasses.road_lane.RoadLane", "road_id": 42, "lane_num": 0}, {"py/object": "db.dataclasses.road_lane.RoadLane", "road_id": 42, "lane_num": 1}], [{"py/object": "db.dataclasses.road_lane.RoadLane", "road_id": 88, "lane_num": 0}, {"py/object": "db.dataclasses.road_lane.RoadLane", "road_id": 88, "lane_num": 1}]], "traffic_lights_coords": [{"py/object": "server.geometry.point.Point", "_Point__x": 22.63993, "_Point__y": 162.82938000000001}, {"py/object": "server.geometry.point.Point", "_Point__x": 22.8036, "_Point__y": 156.83613}], "num_traffic_lights": 2}, {"py/object": "db.dataclasses.junction_data.JunctionData", "idnum": 82, "coordinates": [{"py/object": "server.geometry.point.Point", "_Point__x": 38.71539, "_Point__y": 158.08461}, {"py/object": "server.geometry.point.Point", "_Point__x": 41.91539, "_Point__y": 158.08461}, {"py/object": "server.geometry.point.Point", "_Point__x": 40.70101, "_Point__y": 161.04521}, {"py/object": "server.geometry.point.Point", "_Point__x": 38.71539, "_Point__y": 161.28461}], "goes_to": [{"py/tuple": [{"py/object": "db.dataclasses.road_lane.RoadLane", "road_id": 89, "lane_num": 0}, {"py/object": "db.dataclasses.road_lane.RoadLane", "road_id": 88, "lane_num": 1}]}, {"py/tuple": [{"py/object": "db.dataclasses.road_lane.RoadLane", "road_id": 89, "lane_num": 1}, {"py/object": "db.dataclasses.road_lane.RoadLane", "road_id": 76, "lane_num": 1}]}, {"py/tuple": [{"py/object": "db.dataclasses.road_lane.RoadLane", "road_id": 89, "lane_num": 2}, {"py/object": "db.dataclasses.road_lane.RoadLane", "road_id": 98, "lane_num": 1}]}], "traffic_lights": [], "traffic_lights_coords": [], "num_traffic_lights": 0}, {"py/object": "db.dataclasses.junction_data.JunctionData", "idnum": 83, "coordinates": [{"py/object": "server.geometry.point.Point", "_Point__x": 59.0, "_Point__y": 159.0}, {"py/object": "server.geometry.point.Point", "_Point__x": 61.0, "_Point__y": 159.0}, {"py/object": "server.geometry.point.Point", "_Point__x": 61.0, "_Point__y": 161.0}, {"py/object": "server.geometry.point.Point", "_Point__x": 59.0, "_Point__y": 161.0}], "goes_to": [{"py/tuple": [{"py/object": "db.dataclasses.road_lane.RoadLane", "road_id": 31, "lane_num": 0}, {"py/object": "db.dataclasses.road_lane.RoadLane", "road_id": 49, "lane_num": 0}]}, {"py/tuple": [{"py/object": "db.dataclasses.road_lane.RoadLane", "road_id": 31, "lane_num": 1}, {"py/object": "db.dataclasses.road_lane.RoadLane", "road_id": 5, "lane_num": 0}]}, {"py/tuple": [{"py/object": "db.dataclasses.road_lane.RoadLane", "road_id": 98, "lane_num": 0}, {"py/object": "db.dataclasses.road_lane.RoadLane", "road_id": 5, "lane_num": 0}]}, {"py/tuple": [{"py/object": "db.dataclasses.road_lane.RoadLane", "road_id": 98, "lane_num": 1}, {"py/object": "db.dataclasses.road_lane.RoadLane", "road_id": 49, "lane_num": 0}]}], "traffic_lights": [[{"py/object": "db.dataclasses.road_lane.RoadLane", "road_id": 31, "lane_num": 0}, {"py/object": "db.dataclasses.road_lane.RoadLane", "road_id": 31, "lane_num": 1}], [{"py/object": "db.dataclasses.road_lane.RoadLane", "road_id": 98, "lane_num": 0}, {"py/object": "db.dataclasses.road_lane.RoadLane", "road_id": 98, "lane_num": 1}]], "traffic_lights_coords": [{"py/object": "server.geometry.point.Point", "_Point__x": 63.0, "_Point__y": 157.0}, {"py/object": "server.geometry.point.Point", "_Point__x": 57.0, "_Point__y": 163.0}], "num_traffic_lights": 2}, {"py/object": "db.dataclasses.junction_data.JunctionData", "idnum": 85, "coordinates": [{"py/object": "server.geometry.point.Point", "_Point__x": 99.0, "_Point__y": 159.0}, {"py/object": "server.geometry.point.Point", "_Point__x": 101.0, "_Point__y": 159.0}, {"py/object": "server.geometry.point.Point", "_Point__x": 101.0, "_Point__y": 161.0}, {"py/object": "server.geometry.point.Point", "_Point__x": 99.0, "_Point__y": 161.0}], "goes_to": [{"py/tuple": [{"py/object": "db.dataclasses.road_lane.RoadLane", "road_id": 26, "lane_num": 0}, {"py/object": "db.dataclasses.road_lane.RoadLane", "road_id": 81, "lane_num": 0}]}, {"py/tuple": [{"py/object": "db.dataclasses.road_lane.RoadLane", "road_id": 26, "lane_num": 1}, {"py/object": "db.dataclasses.road_lane.RoadLane", "road_id": 39, "lane_num": 0}]}, {"py/tuple": [{"py/object": "db.dataclasses.road_lane.RoadLane", "road_id": 26, "lane_num": 2}, {"py/object": "db.dataclasses.road_lane.RoadLane", "road_id": 14, "lane_num": 0}]}], "traffic_lights": [], "traffic_lights_coords": [], "num_traffic_lights": 0}, {"py/object": "db.dataclasses.junction_data.JunctionData", "idnum": 87, "coordinates": [{"py/object": "server.geometry.point.Point", "_Point__x": 138.83399, "_Point__y": 158.4888}, {"py/object": "server.geometry.point.Point", "_Point__x": 140.8036, "_Point__y": 158.83613}, {"py/object": "server.geometry.point.Point", "_Point__x": 140.63993, "_Point__y": 160.82938000000001}, {"py/object": "server.geometry.point.Point", "_Point__x": 138.83399, "_Point__y": 161.68879}], "goes_to": [{"py/tuple": [{"py/object": "db.dataclasses.road_lane.RoadLane", "road_id": 65, "lane_num": 0}, {"py/object": "db.dataclasses.road_lane.RoadLane", "road_id": 64, "lane_num": 1}]}, {"py/tuple": [{"py/object": "db.dataclasses.road_lane.RoadLane", "road_id": 68, "lane_num": 0}, {"py/object": "db.dataclasses.road_lane.RoadLane", "road_id": 64, "lane_num": 1}]}, {"py/tuple": [{"py/object": "db.dataclasses.road_lane.RoadLane", "road_id": 80, "lane_num": 0}, {"py/object": "db.dataclasses.road_lane.RoadLane", "road_id": 64, "lane_num": 1}]}], "traffic_lights": [[{"py/object": "db.dataclasses.road_lane.RoadLane", "road_id": 65, "lane_num": 0}], [{"py/object": "db.dataclasses.road_lane.RoadLane", "road_id": 68, "lane_num": 0}], [{"py/object": "db.dataclasses.road_lane.RoadLane", "road_id": 80, "lane_num": 0}]], "traffic_lights_coords": [{"py/object": "server.geometry.point.Point", "_Point__x": 142.8036, "_Point__y": 156.83613}, {"py/object": "server.geometry.point.Point", "_Point__x": 136.83399, "_Point__y": 156.4888}, {"py/object": "server.geometry.point.Point", "_Point__x": 142.63993, "_Point__y": 162.82938000000001}], "num_traffic_lights": 3}, {"py/object": "db.dataclasses.junction_data.JunctionData", "idnum": 89, "coordinates": [{"py/object": "server.geometry.point.Point", "_Point__x": 179.0, "_Point__y": 159.0}, {"py/object": "server.geometry.point.Point", "_Point__x": 181.0, "_Point__y": 159.0}, {"py/object": "server.geometry.point.Point", "_Point__x": 181.0, "_Point__y": 161.0}, {"py/object": "server.geometry.point.Point", "_Point__x": 179.0, "_Point__y": 161.0}], "goes_to": [{"py/tuple": [{"py/object": "db.dataclasses.road_lane.RoadLane", "road_id": 86, "lane_num": 0}, {"py/object": "db.dataclasses.road_lane.RoadLane", "road_id": 58, "lane_num": 0}]}, {"py/tuple": [{"py/object": "db.dataclasses.road_lane.RoadLane", "road_id": 86, "lane_num": 1}, {"py/object": "db.dataclasses.road_lane.RoadLane", "road_id": 77, "lane_num": 0}]}], "traffic_lights": [], "traffic_lights_coords": [], "num_traffic_lights": 0}, {"py/object": "db.dataclasses.junction_data.JunctionData", "idnum": 91, "coordinates": [{"py/object": "server.geometry.point.Point", "_Point__x": 18.71423, "_Point__y": 178.58929}, {"py/object": "server.geometry.point.Point", "_Point__x": 21.86561, "_Point__y": 179.14499}, {"py/object": "server.geometry.point.Point", "_Point__x": 20.70566, "_Point__y": 180.77426}, {"py/object": "server.geometry.point.Point", "_Point__x": 18.71423, "_Point__y": 180.5893}], "goes_to": [{"py/tuple": [{"py/object": "db.dataclasses.road_lane.RoadLane", "road_id": 55, "lane_num": 0}, {"py/object": "db.dataclasses.road_lane.RoadLane", "road_id": 42, "lane_num": 1}]}, {"py/tuple": [{"py/object": "db.dataclasses.road_lane.RoadLane", "road_id": 55, "lane_num": 1}, {"py/object": "db.dataclasses.road_lane.RoadLane", "road_id": 2, "lane_num": 0}]}], "traffic_lights": [], "traffic_lights_coords": [], "num_traffic_lights": 0}, {"py/object": "db.dataclasses.junction_data.JunctionData", "idnum": 92, "coordinates": [{"py/object": "server.geometry.point.Point", "_Point__x": 39.04218, "_Point__y": 177.76463}, {"py/object": "server.geometry.point.Point", "_Point__x": 42.412780000000005, "_Point__y": 180.59289}, {"py/object": "server.geometry.point.Point", "_Point__x": 40.49025, "_Point__y": 181.61488}, {"py/object": "server.geometry.point.Point", "_Point__x": 39.04218, "_Point__y": 180.23535}], "goes_to": [{"py/tuple": [{"py/object": "db.dataclasses.road_lane.RoadLane", "road_id": 2, "lane_num": 0}, {"py/object": "db.dataclasses.road_lane.RoadLane", "road_id": 89, "lane_num": 2}]}, {"py/tuple": [{"py/object": "db.dataclasses.road_lane.RoadLane", "road_id": 49, "lane_num": 0}, {"py/object": "db.dataclasses.road_lane.RoadLane", "road_id": 89, "lane_num": 2}]}], "traffic_lights": [[{"py/object": "db.dataclasses.road_lane.RoadLane", "road_id": 2, "lane_num": 0}], [{"py/object": "db.dataclasses.road_lane.RoadLane", "road_id": 49, "lane_num": 0}]], "traffic_lights_coords": [{"py/object": "server.geometry.point.Point", "_Point__x": 37.04218, "_Point__y": 182.23535}, {"py/object": "server.geometry.point.Point", "_Point__x": 44.412780000000005, "_Point__y": 178.59289}], "num_traffic_lights": 2}, {"py/object": "db.dataclasses.junction_data.JunctionData", "idnum": 95, "coordinates": [{"py/object": "server.geometry.point.Point", "_Point__x": 98.83399, "_Point__y": 178.4888}, {"py/object": "server.geometry.point.Point", "_Point__x": 100.8036, "_Point__y": 178.83613}, {"py/object": "server.geometry.point.Point", "_Point__x": 100.63993, "_Point__y": 180.82938000000001}, {"py/object": "server.geometry.point.Point", "_Point__x": 98.83399, "_Point__y": 181.68879}], "goes_to": [{"py/tuple": [{"py/object": "db.dataclasses.road_lane.RoadLane", "road_id": 81, "lane_num": 0}, {"py/object": "db.dataclasses.road_lane.RoadLane", "road_id": 31, "lane_num": 1}]}, {"py/tuple": [{"py/object": "db.dataclasses.road_lane.RoadLane", "road_id": 90, "lane_num": 0}, {"py/object": "db.dataclasses.road_lane.RoadLane", "road_id": 31, "lane_num": 1}]}], "traffic_lights": [[{"py/object": "db.dataclasses.road_lane.RoadLane", "road_id": 81, "lane_num": 0}], [{"py/object": "db.dataclasses.road_lane.RoadLane", "road_id": 90, "lane_num": 0}]], "traffic_lights_coords": [{"py/object": "server.geometry.point.Point", "_Point__x": 96.83399, "_Point__y": 176.4888}, {"py/object": "server.geometry.point.Point", "_Point__x": 102.8036, "_Point__y": 176.83613}], "num_traffic_lights": 2}, {"py/object": "db.dataclasses.junction_data.JunctionData", "idnum": 96, "coordinates": [{"py/object": "server.geometry.point.Point", "_Point__x": 119.32541, "_Point__y": 178.67459}, {"py/object": "server.geometry.point.Point", "_Point__x": 121.32541, "_Point__y": 178.67459}, {"py/object": "server.geometry.point.Point", "_Point__x": 120.94241000000001, "_Point__y": 181.85159}, {"py/object": "server.geometry.point.Point", "_Point__x": 119.32541, "_Point__y": 180.6746}], "goes_to": [{"py/tuple": [{"py/object": "db.dataclasses.road_lane.RoadLane", "road_id": 64, "lane_num": 0}, {"py/object": "db.dataclasses.road_lane.RoadLane", "road_id": 83, "lane_num": 1}]}, {"py/tuple": [{"py/object": "db.dataclasses.road_lane.RoadLane", "road_id": 64, "lane_num": 1}, {"py/object": "db.dataclasses.road_lane.RoadLane", "road_id": 90, "lane_num": 0}]}], "traffic_lights": [], "traffic_lights_coords": [], "num_traffic_lights": 0}, {"py/object": "db.dataclasses.junction_data.JunctionData", "idnum": 97, "coordinates": [{"py/object": "server.geometry.point.Point", "_Point__x": 139.0, "_Point__y": 179.0}, {"py/object": "server.geometry.point.Point", "_Point__x": 141.0, "_Point__y": 179.0}, {"py/object": "server.geometry.point.Point", "_Point__x": 141.0, "_Point__y": 181.0}, {"py/object": "server.geometry.point.Point", "_Point__x": 139.0, "_Point__y": 181.0}], "goes_to": [{"py/tuple": [{"py/object": "db.dataclasses.road_lane.RoadLane", "road_id": 83, "lane_num": 0}, {"py/object": "db.dataclasses.road_lane.RoadLane", "road_id": 80, "lane_num": 0}]}, {"py/tuple": [{"py/object": "db.dataclasses.road_lane.RoadLane", "road_id": 83, "lane_num": 1}, {"py/object": "db.dataclasses.road_lane.RoadLane", "road_id": 102, "lane_num": 0}]}], "traffic_lights": [], "traffic_lights_coords": [], "num_traffic_lights": 0}, {"py/object": "db.dataclasses.junction_data.JunctionData", "idnum": 98, "coordinates": [{"py/object": "server.geometry.point.Point", "_Point__x": 159.0, "_Point__y": 179.0}, {"py/object": "server.geometry.point.Point", "_Point__x": 161.0, "_Point__y": 179.0}, {"py/object": "server.geometry.point.Point", "_Point__x": 161.0, "_Point__y": 181.0}, {"py/object": "server.geometry.point.Point", "_Point__x": 159.0, "_Point__y": 181.0}], "goes_to": [{"py/tuple": [{"py/object": "db.dataclasses.road_lane.RoadLane", "road_id": 58, "lane_num": 0}, {"py/object": "db.dataclasses.road_lane.RoadLane", "road_id": 65, "lane_num": 0}]}, {"py/tuple": [{"py/object": "db.dataclasses.road_lane.RoadLane", "road_id": 102, "lane_num": 0}, {"py/object": "db.dataclasses.road_lane.RoadLane", "road_id": 65, "lane_num": 0}]}], "traffic_lights": [[{"py/object": "db.dataclasses.road_lane.RoadLane", "road_id": 58, "lane_num": 0}], [{"py/object": "db.dataclasses.road_lane.RoadLane", "road_id": 102, "lane_num": 0}]], "traffic_lights_coords": [{"py/object": "server.geometry.point.Point", "_Point__x": 163.0, "_Point__y": 177.0}, {"py/object": "server.geometry.point.Point", "_Point__x": 157.0, "_Point__y": 183.0}], "num_traffic_lights": 2}]